anaconda_cli_base/__init__.py
anaconda_cli_base/_version.py
anaconda_cli_base/cli.py
anaconda_cli_base/config.py
anaconda_cli_base/console.py
anaconda_cli_base/deprecations.py
anaconda_cli_base/exceptions.py
anaconda_cli_base/plugins.py
anaconda_cli_base/py.typed
anaconda_cli_base-0.8.0.dist-info/METADATA
anaconda_cli_base-0.8.0.dist-info/WHEEL
anaconda_cli_base-0.8.0.dist-info/entry_points.txt
anaconda_cli_base-0.8.0.dist-info/licenses/LICENSE
anaconda_cli_base-0.8.0.dist-info/RECORD
