Metadata-Version: 2.4
Name: anaconda-cli-base
Version: 0.8.0
Summary: A base CLI entrypoint supporting Anaconda CLI plugins
License: BSD-3-Clause
License-File: LICENSE
Requires-Python: >=3.10
Requires-Dist: click
Requires-Dist: packaging>=23.0
Requires-Dist: pydantic-settings>=2.3
Requires-Dist: readchar
Requires-Dist: rich
Requires-Dist: tomli
Requires-Dist: tomlkit
Requires-Dist: typer>=0.17
Provides-Extra: dev
Requires-Dist: mypy; extra == 'dev'
Requires-Dist: pytest; extra == 'dev'
Requires-Dist: pytest-cov; extra == 'dev'
Requires-Dist: pytest-mock; extra == 'dev'
Requires-Dist: tox; extra == 'dev'
Requires-Dist: types-requests; extra == 'dev'
Provides-Extra: publish
Requires-Dist: build; extra == 'publish'
Requires-Dist: twine; extra == 'publish'
Requires-Dist: wheel; extra == 'publish'
